lutv/__init__.py
lutv/random.py
lutv-1.0.1.dist-info/LICENSE
lutv-1.0.1.dist-info/METADATA
lutv-1.0.1.dist-info/WHEEL
lutv-1.0.1.dist-info/top_level.txt
lutv-1.0.1.dist-info/RECORD
