Metadata-Version: 2.1
Name: lutv
Version: 1.0.1
Summary: This is my personal project
Author: =?utf-8?b?VHLhuqduIFh1w6JuIEzhu6Np?=
Author-email: tranxuanloi2007@gmail.com
Keywords: LuTV,lutv,random,random_uer,lutvrandom,LuTV Random User,Tranxuanloi,TranXuanLoi,tranxuanloi,tranxuanloi2007
Classifier: Development Status :: 1 - Planning
Classifier: Intended Audience :: Developers
Classifier: Programming Language :: Python :: 3
Classifier: Operating System :: Unix
Classifier: Operating System :: Android
Classifier: Operating System :: MacOS :: MacOS X
Classifier: Operating System :: Microsoft :: Windows
License-File: LICENSE
